langfuse_mcp/__init__.py
langfuse_mcp/__main__.py
langfuse_mcp_better-1.4.2.dist-info/METADATA
langfuse_mcp_better-1.4.2.dist-info/WHEEL
langfuse_mcp_better-1.4.2.dist-info/entry_points.txt
langfuse_mcp_better-1.4.2.dist-info/licenses/LICENSE
langfuse_mcp_better-1.4.2.dist-info/RECORD
