Metadata-Version: 2.4
Name: langfuse-mcp-better
Version: 1.4.2
Summary: Enhanced Langfuse MCP server with training data extraction for fine-tuning and reinforcement learning. Supports LangGraph node filtering and multiple output formats.
Project-URL: Homepage, https://github.com/futumaster/langfuse-mcp-better
Project-URL: Repository, https://github.com/futumaster/langfuse-mcp-better
Project-URL: Issues, https://github.com/futumaster/langfuse-mcp-better/issues
Project-URL: Original Project, https://github.com/avivsinai/langfuse-mcp
Author-email: Aviv Sinai <avivsinai@gmail.com>, Wenxin Huang <wenxinhuang@example.com>
License: MIT
License-File: LICENSE
Classifier: Development Status :: 4 - Beta
Classifier: Intended Audience :: Developers
Classifier: License :: OSI Approved :: MIT License
Classifier: Programming Language :: Python :: 3
Classifier: Programming Language :: Python :: 3 :: Only
Classifier: Programming Language :: Python :: 3.10
Classifier: Programming Language :: Python :: 3.11
Classifier: Programming Language :: Python :: 3.12
Classifier: Programming Language :: Python :: 3.13
Requires-Python: <3.14,>=3.10
Requires-Dist: cachetools>=5.0.0
Requires-Dist: langfuse<4.0.0,>=3.0.0
Requires-Dist: mcp[cli]>=1.6.0
Requires-Dist: pydantic>=2.0.0
Provides-Extra: dev
Requires-Dist: pytest; extra == 'dev'
Requires-Dist: pytest-asyncio; extra == 'dev'
Requires-Dist: pytest-mock; extra == 'dev'
Requires-Dist: ruff; extra == 'dev'
